gridstitcher/__init__.py
gridstitcher/_modidx.py
gridstitcher/core.py
gridstitcher/stitcher.py
gridstitcher-0.0.1.dist-info/LICENSE
gridstitcher-0.0.1.dist-info/METADATA
gridstitcher-0.0.1.dist-info/WHEEL
gridstitcher-0.0.1.dist-info/entry_points.txt
gridstitcher-0.0.1.dist-info/top_level.txt
gridstitcher-0.0.1.dist-info/RECORD
