Metadata-Version: 2.1
Name: gridstitcher
Version: 0.0.1
Summary: Experimental package to automate stitching/registration of a regular grid of image tiles.
Home-page: https://github.com/fligt/gridstitcher
Author: Frank Ligterink
Author-email: frank.ligterink@gmail.com
License: MIT License
Keywords: nbdev jupyter notebook python
Classifier: Development Status :: 4 - Beta
Classifier: Intended Audience :: Developers
Classifier: Natural Language :: English
Classifier: Programming Language :: Python :: 3.7
Classifier: Programming Language :: Python :: 3.8
Classifier: Programming Language :: Python :: 3.9
Classifier: Programming Language :: Python :: 3.10
Classifier: Programming Language :: Python :: 3.11
Classifier: Programming Language :: Python :: 3.12
Classifier: License :: OSI Approved :: MIT License
Requires-Python: >=3.7
License-File: LICENSE
Requires-Dist: numpy
Requires-Dist: matplotlib
Requires-Dist: opencv-python
Requires-Dist: scipy
Requires-Dist: imageio
Provides-Extra: dev
